{
    "name": "CPU_XS_FUNC_DLSM_CAP_MSR",
    "cmdline": "dlsm_func.sh -s dlsm_msr_cap -p \"0x2b3\"",
    "initial_platform": "Clearwater Forest",
    "summary": "Check DLSM basic cap rdmsr 0x2b3, could read expected value",
    "status": "Closed",
    "steps": [],
    "flags": [],
    "priority": "P1",
    "scenario": "cpu_dlsm_func_tests",
    "domain": "CPU",
    "feature": "DLSM",
    "owner": "xupengfe",
    "testType": "FUNC",
    "execType": "Auto",
    "poweron": true,
    "presilicon": true,
    "clientOnly": false,
    "serverOnly": false,
    "kparams": [],
    "kconfigs": [],
    "packages": [],
    "bios": [],
    "peripherals": [],
    "createDate": "2023-05-15T15:17:47.000-0800",
    "link": "",
    "tips": ""
}
