{
    "name": "POWER_XS_BAT_ACPI_CPPC_PCORE_SYSFS",
    "initial_platform": "",
    "cmdline": "powermgr_acpi_cppc.sh -t pcore",
    "steps": [],
    "flags": [],
    "summary": "Check cpufeq acpi_cppc sysfs values for each pcore cpu",
    "status": "Closed",
    "priority": "P1",
    "scenario": "powermgr_acpi_cppc_bat_tests",
    "domain": "Power",
    "feature": "Intel_Pstate",
    "owner": "qwang59",
    "testType": "BAT",
    "execType": "Auto",
    "poweron": true,
    "presilicon": true,
    "clientOnly": false,
    "serverOnly": false,
    "kparams": [],
    "kconfigs": [],
    "packages": [
        {
            "Name": "cpuid"
        }
    ],
    "bios": [],
    "peripherals": [],
    "createDate": "2021-10-25T17:00:00.000-0700",
    "link": "",
    "tips": ""
}