{
    "name": "PT_XS_FUNC_SN_PACKGE_EXCLUDE_NO",
    "initial_platform": "",
    "cmdline": "BAT-ipt 4 0",
    "steps": [],
    "flags": [],
    "summary": "Snapshot package check with no exclude with all CPUs",
    "status": "Closed",
    "priority": "P1",
    "scenario": "pt_func_tests",
    "domain": "CPU",
    "feature": "Intel_PT",
    "owner": "feiyi",
    "testType": "FUNC",
    "execType": "Auto",
    "poweron": false,
    "presilicon": true,
    "clientOnly": false,
    "serverOnly": false,
    "kparams": [],
    "kconfigs": [],
    "packages": [],
    "bios": [],
    "peripherals": [],
    "createDate": "2018-07-18T17:00:00.000-0700",
    "link": "",
    "tips": ""
}