{
    "name": "SATA_S_FUNC_IO_1TH_1G",
    "initial_platform": "",
    "cmdline": "blk_device_iozone_readwrite_test.sh -d \"sata\" -s \"1g\" -r \"16k\" -i \"0\" -i \"1\" -i \"2\" -i \"8\"",
    "steps": [],
    "flags": [],
    "summary": "Write/Read data SATA with Iozone with 1 thread with record size of 1G",
    "status": "Closed",
    "priority": "P2",
    "scenario": "sata_iozone_func_tests",
    "domain": "IO",
    "feature": "SATA",
    "owner": "hongyuni",
    "testType": "FUNC",
    "execType": "Auto",
    "poweron": false,
    "presilicon": true,
    "clientOnly": false,
    "serverOnly": false,
    "kparams": [],
    "kconfigs": [],
    "packages": [],
    "bios": [],
    "peripherals": [
        {
            "name": "free sata disk partition",
            "check": "",
            "description": ""
        }
    ],
    "createDate": "2018-04-11T17:00:00.000-0700",
    "link": "",
    "tips": ""
}