{
    "name": "TGPIO_OSE_XS_FUNC_PINS_COUNT",
    "initial_platform": "",
    "cmdline": "tgpio_tests.sh -t pins_count -m ose",
    "steps": [],
    "flags": [],
    "summary": "Check if pin count is correct",
    "status": "Closed",
    "priority": "P1",
    "scenario": "ose_tgpio_func_tests",
    "domain": "OSE",
    "feature": "OSE_TGPIO",
    "owner": "feiyi",
    "testType": "FUNC",
    "execType": "Auto",
    "poweron": false,
    "presilicon": true,
    "clientOnly": false,
    "serverOnly": false,
    "kparams": [],
    "kconfigs": [],
    "packages": [],
    "bios": [],
    "peripherals": [],
    "createDate": "2019-04-27T17:00:00.000-0700",
    "link": "",
    "tips": ""
}