{
    "name": "TH_XS_FUNC_CPU_MSC1_CONSOLE_TRACE_BASIC",
    "initial_platform": "",
    "cmdline": "intel_th_tests.sh -t msu_trace -s console -d 0-msc1 -p basic",
    "steps": [],
    "flags": [],
    "summary": "Check with CPU trace hub target mode, output as msc1, trace input as console with basic profile",
    "status": "Closed",
    "priority": "P2",
    "scenario": "th_target_mode_cpu_func_tests",
    "domain": "CPU",
    "feature": "Intel_TH",
    "owner": "feiyi",
    "testType": "FUNC",
    "execType": "Auto",
    "poweron": false,
    "presilicon": true,
    "clientOnly": false,
    "serverOnly": false,
    "kparams": [],
    "kconfigs": [
        {
            "name": "CONFIG_INTEL_TH",
            "values": [
                "m"
            ],
            "description": ""
        },
        {
            "name": "CONFIG_INTEL_TH_ACPI",
            "values": [
                "m"
            ],
            "description": ""
        },
        {
            "name": "CONFIG_INTEL_TH_GTH",
            "values": [
                "m"
            ],
            "description": ""
        },
        {
            "name": "CONFIG_INTEL_TH_STH",
            "values": [
                "m"
            ],
            "description": ""
        },
        {
            "name": "CONFIG_INTEL_TH_MSU",
            "values": [
                "m"
            ],
            "description": ""
        },
        {
            "name": "CONFIG_INTEL_TH_PTI",
            "values": [
                "m"
            ],
            "description": ""
        },
        {
            "name": "CONFIG_STM",
            "values": [
                "m"
            ],
            "description": ""
        },
        {
            "name": "CONFIG_STM_PROTO_BASIC",
            "values": [
                "m"
            ],
            "description": ""
        },
        {
            "name": "CONFIG_STM_PROTO_SYS_T",
            "values": [
                "m"
            ],
            "description": ""
        },
        {
            "name": "CONFIG_STM_DUMMY",
            "values": [
                "m"
            ],
            "description": ""
        },
        {
            "name": "CONFIG_STM_SOURCE_CONSOLE",
            "values": [
                "m"
            ],
            "description": ""
        }
    ],
    "packages": [],
    "bios": [],
    "peripherals": [],
    "createDate": "2018-12-26T16:00:00.000-0800",
    "link": "",
    "tips": ""
}